hypnomics/__init__.py
hypnomics-1.0.0.dev1.dist-info/LICENSE
hypnomics-1.0.0.dev1.dist-info/METADATA
hypnomics-1.0.0.dev1.dist-info/WHEEL
hypnomics-1.0.0.dev1.dist-info/top_level.txt
hypnomics-1.0.0.dev1.dist-info/RECORD
